{"zip": "45262", "sector": "Industrials", "fullTimeEmployees": 40000, "longBusinessSummary": "Cintas Corporation provides corporate identity uniforms and related business services primarily in North America, Latin America, Europe, and Asia. It operates through Uniform Rental and Facility Services and First Aid and Safety Services segments. The company rents and services uniforms and other garments, including flame resistant clothing, mats, mops and shop towels, and other ancillary items; and provides restroom cleaning services and supplies, and carpet and tile cleaning services, as well as sells uniforms. It also offers first aid and safety services, and fire protection products and services. The company provides its products and services through its distribution network and local delivery routes, or local representatives to small service and manufacturing companies, as well as major corporations. Cintas Corporation was founded in 1968 and is headquartered in Cincinnati, Ohio.", "city": "Cincinnati", "phone": "513 459 1200", "state": "OH", "country": "United States", "companyOfficers": [], "website": "http://www.cintas.com", "maxAge": 1, "address1": "6800 Cintas Boulevard", "industry": "Specialty Business Services", "address2": "PO Box 625737", "previousClose": 352.98, "regularMarketOpen": 352.61, "twoHundredDayAverage": 346.25473, "trailingAnnualDividendYield": 0.012068673, "payoutRatio": 0.4666, "volume24Hr": null, "regularMarketDayHigh": 354.65, "navPrice": null, "averageDailyVolume10Day": 397033, "totalAssets": null, "regularMarketPreviousClose": 352.98, "fiftyDayAverage": 350.74854, "trailingAnnualDividendRate": 4.26, "open": 352.61, "averageVolume10days": 397033, "expireDate": null, "yield": null, "algorithm": null, "dividendRate": 3, "exDividendDate": 1620864000, "beta": 1.504688, "circulatingSupply": null, "startDate": null, "regularMarketDayLow": 351.87, "priceHint": 2, "currency": "USD", "trailingPE": 38.559547, "regularMarketVolume": 327983, "lastMarket": null, "maxSupply": null, "openInterest": null, "marketCap": 37008072704, "volumeAllCurrencies": null, "strikePrice": null, "averageVolume": 402063, "priceToSalesTrailing12Months": 5.363285, "dayLow": 351.87, "ask": 0, "ytdReturn": null, "askSize": 800, "volume": 327983, "fiftyTwoWeekHigh": 369.2, "forwardPE": 34.537254, "fromCurrency": null, "fiveYearAvgDividendYield": 0.99, "fiftyTwoWeekLow": 254.07, "bid": 0, "tradeable": false, "dividendYield": 0.0086, "bidSize": 1200, "dayHigh": 354.65, "exchange": "NMS", "shortName": "Cintas Corporation", "longName": "Cintas Corporation", "exchangeTimezoneName": "America/New_York", "exchangeTimezoneShortName": "EDT", "isEsgPopulated": true, "gmtOffSetMilliseconds": "-14400000", "underlyingSymbol": null, "quoteType": "EQUITY", "symbol": "CTAS", "underlyingExchangeSymbol": null, "headSymbol": null, "messageBoardId": "finmb_260725", "uuid": "1d3d7b01-7703-34ac-ba0b-74dff54e6e3b", "market": "us_market", "annualHoldingsTurnover": null, "enterpriseToRevenue": 5.661, "beta3Year": null, "profitMargins": 0.14316, "enterpriseToEbitda": 25.557, "52WeekChange": null, "morningStarRiskRating": null, "forwardEps": 10.2, "revenueQuarterlyGrowth": null, "sharesOutstanding": 105053000, "fundInceptionDate": null, "annualReportExpenseRatio": null, "bookValue": 36.334, "sharesShort": 857148, "sharesPercentSharesOut": 0.0082, "fundFamily": null, "lastFiscalYearEnd": 1590883200, "heldPercentInstitutions": 0.66704005, "netIncomeToCommon": 980628992, "trailingEps": 9.136, "lastDividendValue": null, "SandP52WeekChange": null, "priceToBook": 9.695602, "heldPercentInsiders": 0.1455, "nextFiscalYearEnd": 1653955200, "mostRecentQuarter": 1614470400, "shortRatio": 2.19, "sharesShortPreviousMonthDate": 1615766400, "floatShares": 89720683, "enterpriseValue": 39063699456, "threeYearAverageReturn": null, "lastSplitDate": 952473600, "lastSplitFactor": "3:2", "legalType": null, "morningStarOverallRating": null, "earningsQuarterlyGrowth": 0.102, "dateShortInterest": 1618444800, "pegRatio": 2.62, "lastCapGain": null, "shortPercentOfFloat": 0.0095999995, "sharesShortPriorMonth": 978787, "category": null, "fiveYearAverageReturn": null, "regularMarketPrice": 352.61, "logo_url": "https://logo.clearbit.com/cintas.com"}