{"zip": "98033", "sector": "Technology", "fullTimeEmployees": 2209, "longBusinessSummary": "Monolithic Power Systems, Inc. designs, develops, and markets integrated power semiconductor solutions and power delivery architectures for computing and storage, automotive, industrial, communications, and consumer applications markets. It offers direct current (DC) to DC integrated circuits (ICs) that are used to convert and control voltages of various electronic systems, such as portable electronic devices, wireless LAN access points, computers and notebooks, monitors, infotainment applications, and medical equipment. The company also provides lighting control ICs for backlighting that are used in systems, which provide the light source for LCD panels in notebook computers, monitors, car navigation systems, and televisions, as well as for general illumination products. The company sells its products through third-party distributors, and value-added resellers, as well as directly to original equipment manufacturers, original design manufacturers, electronic manufacturing service providers, and other end customers in China, Taiwan, Europe, South Korea, Southeast Asia, Japan, the United States, and internationally. Monolithic Power Systems, Inc. was incorporated in 1997 and is headquartered in Kirkland, Washington.", "city": "Kirkland", "phone": "425 296 9956", "state": "WA", "country": "United States", "companyOfficers": [], "website": "http://www.monolithicpower.com", "maxAge": 1, "address1": "5808 Lake Washington Boulevard NE", "industry": "Semiconductors", "previousClose": 342.44, "regularMarketOpen": 342.56, "twoHundredDayAverage": 351.73053, "trailingAnnualDividendYield": 0.0058404393, "payoutRatio": 0.5714, "volume24Hr": null, "regularMarketDayHigh": 345.66, "navPrice": null, "averageDailyVolume10Day": 324250, "totalAssets": null, "regularMarketPreviousClose": 342.44, "fiftyDayAverage": 346.32352, "trailingAnnualDividendRate": 2, "open": 342.56, "averageVolume10days": 324250, "expireDate": null, "yield": null, "algorithm": null, "dividendRate": 2.4, "exDividendDate": 1617062400, "beta": 0.914506, "circulatingSupply": null, "startDate": null, "regularMarketDayLow": 339.411, "priceHint": 2, "currency": "USD", "trailingPE": 98.18, "regularMarketVolume": 293007, "lastMarket": null, "maxSupply": null, "openInterest": null, "marketCap": 15716605952, "volumeAllCurrencies": null, "strikePrice": null, "averageVolume": 415977, "priceToSalesTrailing12Months": 18.611605, "dayLow": 339.411, "ask": 0, "ytdReturn": null, "askSize": 900, "volume": 293007, "fiftyTwoWeekHigh": 406.75, "forwardPE": 50.018925, "fromCurrency": null, "fiveYearAvgDividendYield": 0.84, "fiftyTwoWeekLow": 208.54, "bid": 0, "tradeable": false, "dividendYield": 0.0069, "bidSize": 900, "dayHigh": 345.66, "exchange": "NMS", "shortName": "Monolithic Power Systems, Inc.", "longName": "Monolithic Power Systems, Inc.", "exchangeTimezoneName": "America/New_York", "exchangeTimezoneShortName": "EDT", "isEsgPopulated": false, "gmtOffSetMilliseconds": "-14400000", "underlyingSymbol": null, "quoteType": "EQUITY", "symbol": "MPWR", "underlyingExchangeSymbol": null, "headSymbol": null, "messageBoardId": "finmb_3051626", "uuid": "2665cd8e-db72-383d-862f-8a5fb43ef509", "market": "us_market", "annualHoldingsTurnover": null, "enterpriseToRevenue": 17.35, "beta3Year": null, "profitMargins": 0.19465, "enterpriseToEbitda": 78.822, "52WeekChange": null, "morningStarRiskRating": null, "forwardEps": 6.87, "revenueQuarterlyGrowth": null, "sharesOutstanding": 45737000, "fundInceptionDate": null, "annualReportExpenseRatio": null, "bookValue": 21.353, "sharesShort": 643192, "sharesPercentSharesOut": 0.014099999, "fundFamily": null, "lastFiscalYearEnd": 1609372800, "heldPercentInstitutions": 0.96667, "netIncomeToCommon": 164375008, "trailingEps": 3.5, "lastDividendValue": null, "SandP52WeekChange": null, "priceToBook": 16.092821, "heldPercentInsiders": 0.024449999, "nextFiscalYearEnd": 1672444800, "mostRecentQuarter": 1609372800, "shortRatio": 1.58, "sharesShortPreviousMonthDate": 1615766400, "floatShares": 42941679, "enterpriseValue": 14650874880, "threeYearAverageReturn": null, "lastSplitDate": null, "lastSplitFactor": null, "legalType": null, "morningStarOverallRating": null, "earningsQuarterlyGrowth": 0.322, "dateShortInterest": 1618444800, "pegRatio": 2.04, "lastCapGain": null, "shortPercentOfFloat": 0.0162, "sharesShortPriorMonth": 607944, "category": null, "fiveYearAverageReturn": null, "regularMarketPrice": 342.56, "logo_url": "https://logo.clearbit.com/monolithicpower.com"}