{"zip": "30326", "sector": "Consumer Cyclical", "fullTimeEmployees": 5249, "longBusinessSummary": "PulteGroup, Inc., through its subsidiaries, primarily engages in the homebuilding business in the United States. The company acquires and develops land primarily for residential purposes; and constructs housing on such land. It offers various home designs, including single-family detached, townhouses, condominiums, and duplexes under the Centex, Pulte Homes, Del Webb, DiVosta Homes, American West, and John Wieland Homes and Neighborhoods brand names. As of December 31, 2020, the company controlled 180,352 lots, of which 91,363 were owned and 88,989 were under land option agreements. It also arranges financing through the origination of mortgage loans primarily for homebuyers; sells the servicing rights for the originated loans; and provides title insurance policies, and examination and closing services to homebuyers. The company was formerly known as Pulte Homes, Inc. and changed its name to PulteGroup, Inc. in March 2010. PulteGroup, Inc. was founded in 1950 and is headquartered in Atlanta, Georgia.", "city": "Atlanta", "phone": "404-978-6400", "state": "GA", "country": "United States", "companyOfficers": [], "website": "http://www.pultegroup.com", "maxAge": 1, "address1": "3350 Peachtree Road NE", "industry": "Residential Construction", "address2": "Suite 150", "previousClose": 58.16, "regularMarketOpen": 58.16, "twoHundredDayAverage": 48.97711, "trailingAnnualDividendYield": 0.0085969735, "payoutRatio": 0.0934, "volume24Hr": null, "regularMarketDayHigh": 58.61, "navPrice": null, "averageDailyVolume10Day": 2756200, "totalAssets": null, "regularMarketPreviousClose": 58.16, "fiftyDayAverage": 57.094707, "trailingAnnualDividendRate": 0.5, "open": 58.16, "averageVolume10days": 2756200, "expireDate": null, "yield": null, "algorithm": null, "dividendRate": 0.56, "exDividendDate": 1615420800, "beta": 1.439051, "circulatingSupply": null, "startDate": null, "regularMarketDayLow": 56.8, "priceHint": 2, "currency": "USD", "trailingPE": 10.292481, "regularMarketVolume": 2897540, "lastMarket": null, "maxSupply": null, "openInterest": null, "marketCap": 15083729920, "volumeAllCurrencies": null, "strikePrice": null, "averageVolume": 2904776, "priceToSalesTrailing12Months": 1.3149569, "dayLow": 56.8, "ask": 0, "ytdReturn": null, "askSize": 1200, "volume": 2897540, "fiftyTwoWeekHigh": 63.91, "forwardPE": 6.638889, "fromCurrency": null, "fiveYearAvgDividendYield": 1.36, "fiftyTwoWeekLow": 31.55, "bid": 0, "tradeable": false, "dividendYield": 0.0092, "bidSize": 800, "dayHigh": 58.61, "exchange": "NYQ", "shortName": "PulteGroup, Inc.", "longName": "PulteGroup, Inc.", "exchangeTimezoneName": "America/New_York", "exchangeTimezoneShortName": "EDT", "isEsgPopulated": true, "gmtOffSetMilliseconds": "-14400000", "underlyingSymbol": null, "quoteType": "EQUITY", "symbol": "PHM", "underlyingExchangeSymbol": null, "headSymbol": null, "messageBoardId": "finmb_294550", "uuid": "9624adff-51b6-3616-bf4f-260872454b5a", "market": "us_market", "annualHoldingsTurnover": null, "enterpriseToRevenue": 1.465, "beta3Year": null, "profitMargins": 0.1314, "enterpriseToEbitda": 8.369, "52WeekChange": null, "morningStarRiskRating": null, "forwardEps": 8.64, "revenueQuarterlyGrowth": null, "sharesOutstanding": 262966000, "fundInceptionDate": null, "annualReportExpenseRatio": null, "bookValue": 25.358, "sharesShort": 6897218, "sharesPercentSharesOut": 0.026099999, "fundFamily": null, "lastFiscalYearEnd": 1609372800, "heldPercentInstitutions": 0.90582, "netIncomeToCommon": 1494139008, "trailingEps": 5.573, "lastDividendValue": null, "SandP52WeekChange": null, "priceToBook": 2.2620082, "heldPercentInsiders": 0.03496, "nextFiscalYearEnd": 1672444800, "mostRecentQuarter": 1617148800, "shortRatio": 2.35, "sharesShortPreviousMonthDate": 1615766400, "floatShares": 255684589, "enterpriseValue": 16809021440, "threeYearAverageReturn": null, "lastSplitDate": 1125619200, "lastSplitFactor": "2:1", "legalType": null, "morningStarOverallRating": null, "earningsQuarterlyGrowth": 0.493, "dateShortInterest": 1618444800, "pegRatio": 0.39, "lastCapGain": null, "shortPercentOfFloat": 0.0294, "sharesShortPriorMonth": 5525799, "category": null, "fiveYearAverageReturn": null, "regularMarketPrice": 58.16, "logo_url": "https://logo.clearbit.com/pultegroup.com"}