{"zip": "105-8676", "sector": "Consumer Defensive", "fullTimeEmployees": 9247, "longBusinessSummary": "Nippon Suisan Kaisha, Ltd. engages marine, food products, fine chemicals, distribution, and marine-related/engineering businesses in Japan and internationally. The company engages in the provision of salmon, Alaska pollock, yellowtail, shrimp, tuna, crab, and yellowtail products, as well as fish feed, oil, and meal products. It also produces and sells frozen foods for household and food service use, canned and bottled foods, products made from Alaska pollock surimi, and fish sausage products, as well as chilled foods. In addition, the company produces and supplies fine chemical products, such as eicosapentaenoic acid (EPA) for pharmaceuticals; and ingredients for functional foods, health products, functional foods, supplements, and other health-related foods that contain EPA. Further, it is involved in integrated logistics service business; and building, repairing, and operating ships. The company was founded in 1911 and is headquartered in Tokyo, Japan.", "city": "Tokyo", "country": "Japan", "companyOfficers": [], "website": "http://www.nissui.co.jp", "maxAge": 1, "address1": "Nishi-Shimbashi Square", "industry": "Packaged Foods", "address2": "1-3-1, Nishi-Shimbashi Minato-ku", "previousClose": 511, "regularMarketOpen": 516, "twoHundredDayAverage": 470.40427, "trailingAnnualDividendYield": 0.01663405, "payoutRatio": 0.201, "volume24Hr": null, "regularMarketDayHigh": 530, "navPrice": null, "averageDailyVolume10Day": 1238475, "totalAssets": null, "regularMarketPreviousClose": 511, "fiftyDayAverage": 528.2, "trailingAnnualDividendRate": 8.5, "open": 516, "toCurrency": null, "averageVolume10days": 1238475, "expireDate": null, "yield": null, "algorithm": null, "dividendRate": 8.5, "exDividendDate": 1617062400, "beta": 0.671278, "circulatingSupply": null, "startDate": null, "regularMarketDayLow": 515, "priceHint": 2, "currency": "JPY", "trailingPE": 12.512713, "regularMarketVolume": 1952600, "lastMarket": null, "maxSupply": null, "openInterest": null, "marketCap": 164593582080, "volumeAllCurrencies": null, "strikePrice": null, "averageVolume": 1872129, "priceToSalesTrailing12Months": 0.2492377, "dayLow": 515, "ask": 0, "ytdReturn": null, "askSize": 0, "volume": 1952600, "fiftyTwoWeekHigh": 573, "forwardPE": 9.374446, "fromCurrency": null, "fiveYearAvgDividendYield": 1.33, "fiftyTwoWeekLow": 400, "bid": 0, "tradeable": false, "dividendYield": 0.0166, "bidSize": 0, "dayHigh": 530, "exchange": "JPX", "shortName": "NIPPON SUISAN KAISHA", "longName": "Nippon Suisan Kaisha, Ltd.", "exchangeTimezoneName": "Asia/Tokyo", "exchangeTimezoneShortName": "JST", "isEsgPopulated": false, "gmtOffSetMilliseconds": "32400000", "underlyingSymbol": null, "quoteType": "EQUITY", "symbol": "1332.T", "underlyingExchangeSymbol": null, "headSymbol": null, "messageBoardId": "finmb_873826", "uuid": "8dbd0719-59ea-3ffc-80b4-773864ebe373", "market": "jp_market", "annualHoldingsTurnover": null, "enterpriseToRevenue": 0.553, "beta3Year": null, "profitMargins": 0.019919999, "enterpriseToEbitda": 9.263, "52WeekChange": 0.11572051, "morningStarRiskRating": null, "forwardEps": 56.43, "revenueQuarterlyGrowth": null, "sharesOutstanding": 311140992, "fundInceptionDate": null, "annualReportExpenseRatio": null, "bookValue": 529.68, "sharesShort": null, "sharesPercentSharesOut": null, "fundFamily": null, "lastFiscalYearEnd": 1585612800, "heldPercentInstitutions": 0.4745, "netIncomeToCommon": 13153999872, "trailingEps": 42.277, "lastDividendValue": 4.5, "SandP52WeekChange": 0.44648218, "priceToBook": 0.99871624, "heldPercentInsiders": 0.095979996, "nextFiscalYearEnd": 1648684800, "mostRecentQuarter": 1609372800, "shortRatio": null, "sharesShortPreviousMonthDate": null, "floatShares": 298808343, "enterpriseValue": 365229899776, "threeYearAverageReturn": null, "lastSplitDate": null, "lastSplitFactor": null, "legalType": null, "lastDividendDate": 1617062400, "morningStarOverallRating": null, "earningsQuarterlyGrowth": 0.17, "dateShortInterest": null, "pegRatio": null, "lastCapGain": null, "shortPercentOfFloat": null, "sharesShortPriorMonth": null, "impliedSharesOutstanding": null, "category": null, "fiveYearAverageReturn": null, "regularMarketPrice": 529, "logo_url": "https://logo.clearbit.com/nissui.co.jp"}