{"zip": "102-8660", "sector": "Financial Services", "fullTimeEmployees": 2268, "longBusinessSummary": "Aozora Bank, Ltd., together with its subsidiaries, provides various banking products and services in Japan and internationally. It operates through Retail Banking Group, Institutional Banking Group, Allied Banking Group, Specialty Finance Group, International Finance Group, and Financial Markets Group segments. The company offers checking accounts, savings accounts, time deposits, deposits-at-notice, non-residents deposits, and negotiable certificates of deposit, as well as deposits in foreign currencies. It also provides loans on deeds, loans on notes, and overdrafts; discount on promissory notes; securities investments, including public, local, and corporate bonds, as well as equity and other securities; domestic and foreign exchange services; and consignment of bonds. In addition, the company offers liabilities guarantee, securities lending, public bonds underwriting, agency, custody, and financial instruments intermediary services. Further, it is involved in the over-the-counter sale of securities investment trusts and insurance products; and provision of trust services for secured corporate bonds, as well as interest rate, currency, and other derivative transaction services. Additionally, the company offers asset management consultation, merger and acquisition advisory, business succession, acquisition and project financing, and equity financing through private equity fund services; syndicated loans arrangements; asset securitization, real estate finance and business recovery finance, and corporate finance services; project financing services in the areas of shipping and trade; other structured finance services; and derivative products and trust services. As of March 31, 2020, it operated 20 domestic offices. The company was formerly known as Nippon Fudosan Bank, Limited and changed its name to Aozora Bank, Ltd. in 2001. Aozora Bank, Ltd. was founded in 1957 and is headquartered in Tokyo, Japan.", "city": "Tokyo", "phone": "81 3 6752 1111", "country": "Japan", "companyOfficers": [], "website": "http://www.aozorabank.co.jp", "maxAge": 1, "address1": "6-1-1, Kojimachi", "industry": "Banks\u2014Regional", "address2": "Chiyoda-ku", "previousClose": 2354, "regularMarketOpen": 2383, "twoHundredDayAverage": 2021.7943, "trailingAnnualDividendYield": 0.05480034, "payoutRatio": 0.7393, "volume24Hr": null, "regularMarketDayHigh": 2423, "navPrice": null, "averageDailyVolume10Day": 1266800, "totalAssets": null, "regularMarketPreviousClose": 2354, "fiftyDayAverage": 2450.9443, "trailingAnnualDividendRate": 129, "open": 2383, "averageVolume10days": 1266800, "expireDate": null, "yield": null, "algorithm": null, "dividendRate": 128, "exDividendDate": 1617062400, "beta": 0.840066, "circulatingSupply": null, "startDate": null, "regularMarketDayLow": 2385, "priceHint": 2, "currency": "JPY", "trailingPE": 13.775636, "regularMarketVolume": 791800, "lastMarket": null, "maxSupply": null, "openInterest": null, "marketCap": 280554012672, "volumeAllCurrencies": null, "strikePrice": null, "averageVolume": 1231659, "priceToSalesTrailing12Months": 2.6095862, "dayLow": 2385, "ask": 2421, "ytdReturn": null, "askSize": 0, "volume": 791800, "fiftyTwoWeekHigh": 2723, "forwardPE": 6.672218, "fromCurrency": null, "fiveYearAvgDividendYield": 5.27, "fiftyTwoWeekLow": 1687, "bid": 0, "tradeable": false, "dividendYield": 0.0545, "bidSize": 0, "dayHigh": 2423, "exchange": "JPX", "shortName": "AOZORA BANK", "longName": "Aozora Bank, Ltd.", "exchangeTimezoneName": "Asia/Tokyo", "exchangeTimezoneShortName": "JST", "isEsgPopulated": false, "gmtOffSetMilliseconds": "32400000", "underlyingSymbol": null, "quoteType": "EQUITY", "symbol": "8304.T", "underlyingExchangeSymbol": null, "headSymbol": null, "messageBoardId": "finmb_874454", "uuid": "f21e946d-86ea-3c47-95d0-60746abdeabe", "market": "jp_market", "annualHoldingsTurnover": null, "enterpriseToRevenue": 2.083, "beta3Year": null, "profitMargins": 0.18969, "enterpriseToEbitda": null, "52WeekChange": null, "morningStarRiskRating": null, "forwardEps": 360.3, "revenueQuarterlyGrowth": null, "sharesOutstanding": 116703000, "fundInceptionDate": null, "annualReportExpenseRatio": null, "bookValue": 4221.696, "sharesShort": null, "sharesPercentSharesOut": null, "fundFamily": null, "lastFiscalYearEnd": 1585612800, "heldPercentInstitutions": 0.31413, "netIncomeToCommon": 20393000960, "trailingEps": 174.511, "lastDividendValue": null, "SandP52WeekChange": null, "priceToBook": 0.5694394, "heldPercentInsiders": 0.00991, "nextFiscalYearEnd": 1648684800, "mostRecentQuarter": 1609372800, "shortRatio": null, "sharesShortPreviousMonthDate": null, "floatShares": 116642184, "enterpriseValue": 223943737344, "threeYearAverageReturn": null, "lastSplitDate": 1506470400, "lastSplitFactor": "1:10", "legalType": null, "morningStarOverallRating": null, "earningsQuarterlyGrowth": -0.276, "dateShortInterest": null, "pegRatio": null, "lastCapGain": null, "shortPercentOfFloat": null, "sharesShortPriorMonth": null, "category": null, "fiveYearAverageReturn": null, "regularMarketPrice": 2404, "logo_url": "https://logo.clearbit.com/aozorabank.co.jp"}