{"zip": "135-8110", "sector": "Technology", "longBusinessSummary": "SCSK Corporation provides information technology (IT) services in Japan and internationally. The company's Manufacturing & Telecommunication Systems Business segment offers IT solutions for core systems, manufacturing and information management systems, supply chain management (SCM), and customer relationship management (CRM) systems for manufacturing, telecommunication, and energy industries. Its Distribution & Media Systems Business segment offers IT solutions, such as core and information systems, SCM, CRM, and e-commerce systems for distribution, service, and media industries. The company's Financial Systems Business segment develops, maintains, and operates systems for banks and trust banks, as well as insurance, securities, lease, and credit companies. Its Global System Solutions & Innovation Business segment provides IT solutions for trading companies. The company's Business Solutions segment provides contact center services; and application management outsourcing services that covers development, installation, maintenance, and operation of enterprise resource planning and CRM products, such as ProActive, SAP, Oracle, and Salesforce, as well as business process outsourcing services. Its IT Platform Solutions segment provides services and products in the fields of IT infrastructure and manufacturing, including computer-aided design and engineering. The company's IT Management segment develops solutions-oriented netXDC data centers to provide outsourcing services; and provides cloud infrastructure, on-site management, and SE support services. Its Mobility System segment offers software solutions for the electronic vehicle unit that controls vehicle's onboard electronics. The company was formerly known as Sumisho Computer Systems Corporation and changed its name to SCSK Corporation in October 2011. The company was founded in 1969 and is headquartered in Tokyo, Japan. SCSK Corporation is a subsidiary of Sumitomo Corporation.", "city": "Tokyo", "phone": "81 3 5166 2500", "country": "Japan", "companyOfficers": [], "website": "http://www.scsk.jp", "maxAge": 1, "address1": "Toyosu Front", "industry": "Information Technology Services", "address2": "3-2-20, Toyosu Koto-ku", "previousClose": 6040, "regularMarketOpen": 6040, "twoHundredDayAverage": 6021.2764, "trailingAnnualDividendYield": 0.01986755, "payoutRatio": 0.38009998, "volume24Hr": null, "regularMarketDayHigh": 6080, "navPrice": null, "averageDailyVolume10Day": 143250, "totalAssets": null, "regularMarketPreviousClose": 6040, "fiftyDayAverage": 6512.778, "trailingAnnualDividendRate": 120, "open": 6040, "averageVolume10days": 143250, "expireDate": null, "yield": null, "algorithm": null, "dividendRate": 140, "exDividendDate": 1632873600, "beta": 1.021582, "circulatingSupply": null, "startDate": null, "regularMarketDayLow": 5930, "priceHint": 2, "currency": "JPY", "trailingPE": 18.70794, "regularMarketVolume": 204200, "lastMarket": null, "maxSupply": null, "openInterest": null, "marketCap": 624030318592, "volumeAllCurrencies": null, "strikePrice": null, "averageVolume": 218154, "priceToSalesTrailing12Months": 1.5724471, "dayLow": 5930, "ask": 0, "ytdReturn": null, "askSize": 0, "volume": 204200, "fiftyTwoWeekHigh": 6810, "forwardPE": 22.443798, "fromCurrency": null, "fiveYearAvgDividendYield": 1.98, "fiftyTwoWeekLow": 4695, "bid": 0, "tradeable": false, "dividendYield": 0.0221, "bidSize": 0, "dayHigh": 6080, "exchange": "JPX", "shortName": "SCSK CORP", "longName": "SCSK Corporation", "exchangeTimezoneName": "Asia/Tokyo", "exchangeTimezoneShortName": "JST", "isEsgPopulated": false, "gmtOffSetMilliseconds": "32400000", "underlyingSymbol": null, "quoteType": "EQUITY", "symbol": "9719.T", "underlyingExchangeSymbol": null, "headSymbol": null, "messageBoardId": "finmb_881041", "uuid": "26863cea-2da4-3ef0-9189-7d9024a2cc35", "market": "jp_market", "annualHoldingsTurnover": null, "enterpriseToRevenue": 1.605, "beta3Year": null, "profitMargins": 0.08425, "enterpriseToEbitda": 9.904, "52WeekChange": null, "morningStarRiskRating": null, "forwardEps": 267.78, "revenueQuarterlyGrowth": null, "sharesOutstanding": 103832000, "fundInceptionDate": null, "annualReportExpenseRatio": null, "bookValue": 2179.906, "sharesShort": null, "sharesPercentSharesOut": null, "fundFamily": null, "lastFiscalYearEnd": 1617148800, "heldPercentInstitutions": 0.1432, "netIncomeToCommon": 33435000832, "trailingEps": 321.254, "lastDividendValue": null, "SandP52WeekChange": null, "priceToBook": 2.7569995, "heldPercentInsiders": 0.55183, "nextFiscalYearEnd": 1680220800, "mostRecentQuarter": 1617148800, "shortRatio": null, "sharesShortPreviousMonthDate": null, "floatShares": 47933883, "enterpriseValue": 636953362432, "threeYearAverageReturn": null, "lastSplitDate": null, "lastSplitFactor": null, "legalType": null, "morningStarOverallRating": null, "earningsQuarterlyGrowth": 0.184, "dateShortInterest": null, "pegRatio": null, "lastCapGain": null, "shortPercentOfFloat": null, "sharesShortPriorMonth": null, "category": null, "fiveYearAverageReturn": null, "regularMarketPrice": 6040, "logo_url": "https://logo.clearbit.com/scsk.jp"}