{"zip": "44308", "sector": "Utilities", "fullTimeEmployees": 12153, "longBusinessSummary": "FirstEnergy Corp., through its subsidiaries, generates, transmits, and distributes electricity in the United States. The company operates through Regulated Distribution and Regulated Transmission segments. It operates 24,035 circuit miles of overhead and underground transmission lines; and electric distribution systems, including 272,531 miles of overhead pole line and underground conduit carrying primary, secondary, and street lighting circuits, as well as owns substations with a total installed transformer capacity of approximately 155,920,348 kilovolt-amperes. The company serves approximately 6 million customers in Ohio, Pennsylvania, West Virginia, Maryland, New Jersey, and New York. FirstEnergy Corp. was incorporated in 1996 and is headquartered in Akron, Ohio.", "city": "Akron", "phone": "800-736-3402", "state": "OH", "country": "United States", "companyOfficers": [], "website": "http://www.firstenergycorp.com", "maxAge": 1, "address1": "76 South Main Street", "industry": "Utilities\u2014Regulated Electric", "previousClose": 38.02, "regularMarketOpen": 38.12, "twoHundredDayAverage": 33.099186, "trailingAnnualDividendYield": 0.041031033, "payoutRatio": 0.6446, "volume24Hr": null, "regularMarketDayHigh": 38.415, "navPrice": null, "averageDailyVolume10Day": 2517566, "totalAssets": null, "regularMarketPreviousClose": 38.02, "fiftyDayAverage": 37.224117, "trailingAnnualDividendRate": 1.56, "open": 38.12, "averageVolume10days": 2517566, "expireDate": null, "yield": null, "algorithm": null, "dividendRate": 1.56, "exDividendDate": 1620259200, "beta": 0.206839, "circulatingSupply": null, "startDate": null, "regularMarketDayLow": 37.845, "priceHint": 2, "currency": "USD", "trailingPE": 15.453809, "regularMarketVolume": 2865181, "lastMarket": null, "maxSupply": null, "openInterest": null, "marketCap": 20744347648, "volumeAllCurrencies": null, "strikePrice": null, "averageVolume": 3660380, "priceToSalesTrailing12Months": 1.952593, "dayLow": 37.845, "ask": 0, "ytdReturn": null, "askSize": 900, "volume": 2865181, "fiftyTwoWeekHigh": 44.1, "forwardPE": 14.669231, "fromCurrency": null, "fiveYearAvgDividendYield": 4.19, "fiftyTwoWeekLow": 22.85, "bid": 0, "tradeable": false, "dividendYield": 0.041300002, "bidSize": 1300, "dayHigh": 38.415, "exchange": "NYQ", "shortName": "FirstEnergy Corp.", "longName": "FirstEnergy Corp.", "exchangeTimezoneName": "America/New_York", "exchangeTimezoneShortName": "EDT", "isEsgPopulated": true, "gmtOffSetMilliseconds": "-14400000", "underlyingSymbol": null, "quoteType": "EQUITY", "symbol": "FE", "underlyingExchangeSymbol": null, "headSymbol": null, "messageBoardId": "finmb_293515", "uuid": "6515f660-56b8-3bca-a61c-a9e02efb3698", "market": "us_market", "annualHoldingsTurnover": null, "enterpriseToRevenue": 4.091, "beta3Year": null, "profitMargins": 0.12613, "enterpriseToEbitda": 11.603, "52WeekChange": null, "morningStarRiskRating": null, "forwardEps": 2.6, "revenueQuarterlyGrowth": null, "sharesOutstanding": 543900032, "fundInceptionDate": null, "annualReportExpenseRatio": null, "bookValue": 13.532, "sharesShort": 22964519, "sharesPercentSharesOut": 0.0422, "fundFamily": null, "lastFiscalYearEnd": 1609372800, "heldPercentInstitutions": 0.81285006, "netIncomeToCommon": 1314000000, "trailingEps": 2.468, "lastDividendValue": null, "SandP52WeekChange": null, "priceToBook": 2.8185043, "heldPercentInsiders": 0.00196, "nextFiscalYearEnd": 1672444800, "mostRecentQuarter": 1617148800, "shortRatio": 5.85, "sharesShortPreviousMonthDate": 1615766400, "floatShares": 542159951, "enterpriseValue": 43465998336, "threeYearAverageReturn": null, "lastSplitDate": 1049414400, "lastSplitFactor": "1:3", "legalType": null, "morningStarOverallRating": null, "earningsQuarterlyGrowth": 3.527, "dateShortInterest": 1618444800, "pegRatio": -7.95, "lastCapGain": null, "shortPercentOfFloat": 0.0479, "sharesShortPriorMonth": 20579505, "category": null, "fiveYearAverageReturn": null, "regularMarketPrice": 38.12, "logo_url": "https://logo.clearbit.com/firstenergycorp.com"}