{"zip": "10504", "sector": "Technology", "fullTimeEmployees": 345900, "longBusinessSummary": "International Business Machines Corporation provides integrated solutions and services worldwide. Its Cloud & Cognitive Software segment offers software for vertical and domain-specific solutions in health, financial services, supply chain, and asset management, weather, and security software and services application areas; and customer information control system and storage, and analytics and integration software solutions to support client mission critical on-premise workloads in banking, airline, and retail industries. It also offers middleware and data platform software, including Red Hat that enables the operation of clients' hybrid multi-cloud environments; and Cloud Paks, WebSphere distributed, and analytics platform software, such as DB2 distributed, information integration, and enterprise content management, as well as IoT, Blockchain and AI/Watson platforms. The company's Global Business Services segment offers business consulting services; system integration, application management, maintenance, and support services for packaged software; and finance, procurement, talent and engagement, and industry-specific business process outsourcing services. Its Global Technology Services segment provides IT infrastructure and platform services; and project, managed, outsourcing, and cloud-delivered services for enterprise IT infrastructure environments; and IT infrastructure support services. The company's Systems segment offers servers for businesses, cloud service providers, and scientific computing organizations; data storage products and solutions; and z/OS, an enterprise operating system, as well as Linux. Its Global Financing segment provides lease, installment payment, loan financing, short-term working capital financing, and remanufacturing and remarketing services. The company was formerly known as Computing-Tabulating-Recording Co. The company was incorporated in 1911 and is headquartered in Armonk, New York.", "city": "Armonk", "phone": "914 499 1900", "state": "NY", "country": "United States", "companyOfficers": [], "website": "http://www.ibm.com", "maxAge": 1, "address1": "One New Orchard Road", "industry": "Information Technology Services", "previousClose": 144.19, "regularMarketOpen": 144.62, "twoHundredDayAverage": 129.66844, "trailingAnnualDividendYield": 0.045218114, "payoutRatio": 1.1087999, "volume24Hr": null, "regularMarketDayHigh": 145.75, "navPrice": null, "averageDailyVolume10Day": 3483333, "totalAssets": null, "regularMarketPreviousClose": 144.19, "fiftyDayAverage": 142.4897, "trailingAnnualDividendRate": 6.52, "open": 144.62, "averageVolume10days": 3483333, "expireDate": null, "yield": null, "algorithm": null, "dividendRate": 6.56, "exDividendDate": 1620345600, "beta": 1.226203, "circulatingSupply": null, "startDate": null, "regularMarketDayLow": 144.13, "priceHint": 2, "currency": "USD", "trailingPE": 24.376045, "regularMarketVolume": 2786916, "lastMarket": null, "maxSupply": null, "openInterest": null, "marketCap": 130204172288, "volumeAllCurrencies": null, "strikePrice": null, "averageVolume": 5392280, "priceToSalesTrailing12Months": 1.7647862, "dayLow": 144.13, "ask": 0, "ytdReturn": null, "askSize": 900, "volume": 2786916, "fiftyTwoWeekHigh": 148.74, "forwardPE": 12.092946, "fromCurrency": null, "fiveYearAvgDividendYield": 4.37, "fiftyTwoWeekLow": 105.92, "bid": 0, "tradeable": false, "dividendYield": 0.0458, "bidSize": 800, "dayHigh": 145.75, "exchange": "NYQ", "shortName": "International Business Machines", "longName": "International Business Machines Corporation", "exchangeTimezoneName": "America/New_York", "exchangeTimezoneShortName": "EDT", "isEsgPopulated": true, "gmtOffSetMilliseconds": "-14400000", "underlyingSymbol": null, "quoteType": "EQUITY", "symbol": "IBM", "underlyingExchangeSymbol": null, "headSymbol": null, "messageBoardId": "finmb_112350", "uuid": "cbf44511-d041-3c6d-9dd7-3cc0c033122c", "market": "us_market", "annualHoldingsTurnover": null, "enterpriseToRevenue": 2.422, "beta3Year": null, "profitMargins": 0.07278, "enterpriseToEbitda": 11.293, "52WeekChange": null, "morningStarRiskRating": null, "forwardEps": 12.05, "revenueQuarterlyGrowth": null, "sharesOutstanding": 893523008, "fundInceptionDate": null, "annualReportExpenseRatio": null, "bookValue": 23.938, "sharesShort": 28585173, "sharesPercentSharesOut": 0.032, "fundFamily": null, "lastFiscalYearEnd": 1609372800, "heldPercentInstitutions": 0.57738996, "netIncomeToCommon": 5280999936, "trailingEps": 5.978, "lastDividendValue": null, "SandP52WeekChange": null, "priceToBook": 6.0873923, "heldPercentInsiders": 0.0013400001, "nextFiscalYearEnd": 1672444800, "mostRecentQuarter": 1617148800, "shortRatio": 4.96, "sharesShortPreviousMonthDate": 1617148800, "floatShares": 891896616, "enterpriseValue": 178673057792, "threeYearAverageReturn": null, "lastSplitDate": 927763200, "lastSplitFactor": "2:1", "legalType": null, "morningStarOverallRating": null, "earningsQuarterlyGrowth": -0.187, "dateShortInterest": 1619740800, "pegRatio": 2.32, "lastCapGain": null, "shortPercentOfFloat": 0.032, "sharesShortPriorMonth": 27009286, "category": null, "fiveYearAverageReturn": null, "regularMarketPrice": 144.62, "logo_url": "https://logo.clearbit.com/ibm.com"}